[{"Collections":[{"sheetName":"Sheet 1","startColumn":"B","endColumn":"P","startRow":"2","endRow":"458","comment":"","rule":"Individual: @B*\nTypes: Author\nFacts: publish @O*\n Facts: affiliatedWith @C*","active":true}]},
{"Collections":[{"sheetName":"Sheet 1","startColumn":"B","endColumn":"P","startRow":"2","endRow":"458","comment":"","rule":"Individual: @N*\nTypes: Reviewer\nFacts: reviews @O*","active":true}]},
{"Collections":[{"sheetName":"Sheet 1","startColumn":"B","endColumn":"P","startRow":"2","endRow":"458","comment":"","rule":"Individual: @E*\nTypes: @J* \n Annotations: edition @L* \n Annotations: volume @F*\n Annotations: issue @P*","active":true}]}]